pyhashlookup/__init__.py
pyhashlookup/api.py
pyhashlookup/py.typed
pyhashlookup-1.2.8.dist-info/LICENSE
pyhashlookup-1.2.8.dist-info/METADATA
pyhashlookup-1.2.8.dist-info/WHEEL
pyhashlookup-1.2.8.dist-info/entry_points.txt
pyhashlookup-1.2.8.dist-info/RECORD
